zev/command_history.py
zev/command_selector.py
zev/constants.py
zev/main.py
zev/utils.py
zev/config/__init__.py
zev/config/setup.py
zev/config/types.py
zev/llms/__init__.py
zev/llms/inference_provider_base.py
zev/llms/llm.py
zev/llms/types.py
zev/llms/azure_openai/__init__.py
zev/llms/azure_openai/provider.py
zev/llms/azure_openai/setup.py
zev/llms/gemini/__init__.py
zev/llms/gemini/provider.py
zev/llms/gemini/setup.py
zev/llms/ollama/__init__.py
zev/llms/ollama/provider.py
zev/llms/ollama/setup.py
zev/llms/openai/__init__.py
zev/llms/openai/provider.py
zev/llms/openai/setup.py
zev-0.8.1.dist-info/licenses/LICENSE
zev-0.8.1.dist-info/METADATA
zev-0.8.1.dist-info/WHEEL
zev-0.8.1.dist-info/entry_points.txt
zev-0.8.1.dist-info/top_level.txt
zev-0.8.1.dist-info/RECORD
