Metadata-Version: 2.4
Name: zev
Version: 0.8.1
Summary: Lookup CLI commands easily
Project-URL: Repository, https://github.com/dtnewman/zev
Requires-Python: >=3.9
License-File: LICENSE
Requires-Dist: openai>=1.72.0
Requires-Dist: pydantic>=2.10.6
Requires-Dist: pyperclip>=1.9.0
Requires-Dist: python-dotenv>=1.0.1
Requires-Dist: questionary>=2.1.0
Requires-Dist: rich>=13.9.4
Provides-Extra: dev
Requires-Dist: ruff>=0.11.2; extra == "dev"
Requires-Dist: isort>=5.13.2; extra == "dev"
Provides-Extra: azure
Requires-Dist: azure-identity>=1.20.0; extra == "azure"
Dynamic: license-file
